{
  "main": {
    "id": "bcbabbd7712bb3e4",
    "type": "split",
    "children": [
      {
        "id": "da4b3102ec62c58c",
        "type": "tabs",
        "children": [
          {
            "id": "c6d6cb6d5a8715cb",
            "type": "leaf",
            "state": {
              "type": "markdown",
              "state": {
                "file": "hot100/16多维动态规划/05编辑距离.md",
                "mode": "source",
                "source": false
              },
              "icon": "lucide-file",
              "title": "05编辑距离"
            }
          }
        ]
      }
    ],
    "direction": "vertical"
  },
  "left": {
    "id": "c43174b04d17e13e",
    "type": "split",
    "children": [
      {
        "id": "40deb40b062b2aff",
        "type": "tabs",
        "children": [
          {
            "id": "79c73542df86e12d",
            "type": "leaf",
            "state": {
              "type": "file-explorer",
              "state": {
                "sortOrder": "alphabetical",
                "autoReveal": false
              },
              "icon": "lucide-folder-closed",
              "title": "文件列表"
            }
          },
          {
            "id": "3fe2189e3b8e16f5",
            "type": "leaf",
            "state": {
              "type": "search",
              "state": {
                "query": "scanner",
                "matchingCase": false,
                "explainSearch": false,
                "collapseAll": false,
                "extraContext": false,
                "sortOrder": "alphabetical"
              },
              "icon": "lucide-search",
              "title": "搜索"
            }
          },
          {
            "id": "945967ee77b0a797",
            "type": "leaf",
            "state": {
              "type": "bookmarks",
              "state": {},
              "icon": "lucide-bookmark",
              "title": "书签"
            }
          }
        ]
      }
    ],
    "direction": "horizontal",
    "width": 325.5
  },
  "right": {
    "id": "ac1f5e81b03a080e",
    "type": "split",
    "children": [
      {
        "id": "57d3bac29e404e9f",
        "type": "tabs",
        "children": [
          {
            "id": "a1db20437bcd108f",
            "type": "leaf",
            "state": {
              "type": "backlink",
              "state": {
                "file": "代码随想录/09动态规划/16爬楼梯进阶版.md",
                "collapseAll": false,
                "extraContext": false,
                "sortOrder": "alphabetical",
                "showSearch": false,
                "searchQuery": "",
                "backlinkCollapsed": false,
                "unlinkedCollapsed": true
              },
              "icon": "links-coming-in",
              "title": "16爬楼梯进阶版 的反向链接列表"
            }
          },
          {
            "id": "7b440070e336c66e",
            "type": "leaf",
            "state": {
              "type": "outgoing-link",
              "state": {
                "linksCollapsed": false,
                "unlinkedCollapsed": true
              },
              "icon": "links-going-out",
              "title": "出链"
            }
          },
          {
            "id": "bbc904119fff9db1",
            "type": "leaf",
            "state": {
              "type": "tag",
              "state": {
                "sortOrder": "frequency",
                "useHierarchy": true,
                "showSearch": false,
                "searchQuery": ""
              },
              "icon": "lucide-tags",
              "title": "标签"
            }
          },
          {
            "id": "95934dceb3388fec",
            "type": "leaf",
            "state": {
              "type": "outline",
              "state": {
                "followCursor": false,
                "showSearch": false,
                "searchQuery": ""
              },
              "icon": "lucide-list",
              "title": "大纲"
            }
          }
        ]
      }
    ],
    "direction": "horizontal",
    "width": 300,
    "collapsed": true
  },
  "left-ribbon": {
    "hiddenItems": {
      "bases:创建新数据库": false,
      "switcher:打开快速切换": false,
      "graph:查看关系图谱": false,
      "canvas:新建白板": false,
      "daily-notes:打开/创建今天的日记": false,
      "templates:插入模板": false,
      "command-palette:打开命令面板": false,
      "obsidian-git:Open Git source control": false
    }
  },
  "active": "c6d6cb6d5a8715cb",
  "lastOpenFiles": [
    "hot100/16多维动态规划/04最长公共子序列.md",
    "hot100/16多维动态规划/03最长回文子串.md",
    "hot100/16多维动态规划/02最小路径和(注意输入).md",
    "hot100/16多维动态规划/01不同路径.md",
    "hot100/15动态规划/10最长的有效括号（多做）.md",
    "hot100/15动态规划/08乘积最大子数组.md",
    "hot100/15动态规划/07最长递增子序列.md",
    "hot100/15动态规划/06单词拆分.md",
    "hot100/15动态规划/04完全平方数.md",
    "代码随想录/09动态规划/40最长回文子序列（不连续）.md",
    "代码随想录/09动态规划/总结.md",
    "代码随想录/09动态规划/39回文子串.md",
    "代码随想录/09动态规划/32最长公共子序列（不连续）.md",
    "代码随想录/09动态规划/22打家劫舍3.md",
    "代码随想录/09动态规划/38编辑距离.md",
    "代码随想录/09动态规划/37两个字符串的删除操作.md",
    "代码随想录/09动态规划/36不同的子序列（多做）.md",
    "代码随想录/09动态规划/35判断子序列.md",
    "代码随想录/09动态规划/34最大子数组和.md",
    "代码随想录/09动态规划/29最长递增子序列（不连续）.md",
    "代码随想录/09动态规划/31最长重复子数组（连续）.md",
    "代码随想录/09动态规划/30最长连续递增子序列.md",
    "代码随想录/09动态规划/28买卖股票的最佳时机含手续费.md",
    "代码随想录/09动态规划/27买卖股票的最佳时机含冷冻期.md",
    "代码随想录/09动态规划/26买卖股票的最佳时机4.md",
    "代码随想录/09动态规划/25买卖股票的最佳时机3.md",
    "代码随想录/08贪心算法/assets/17监控二叉树(多做)",
    "剑指offer/01链表/08删除链表中重复的结点(多做且新).md.baiduyun.uploading.cfg",
    "代码随想录/02链表/总结.md.baiduyun.uploading.cfg",
    "hot100/07链表/10k个一组翻转链表（多做）.md.baiduyun.uploading.cfg",
    "hot100/08二叉树/13路径总和3.md.baiduyun.uploading.cfg",
    "hot100/08二叉树/11二叉树展开为链表（acm多做）.md.baiduyun.uploading.cfg",
    "剑指offer/02二叉树/16序列化二叉树（新且多做）.md.baiduyun.uploading.cfg",
    "剑指offer/02二叉树/13二叉树的下一个节点（新且多做）.md.baiduyun.uploading.cfg",
    "hot100/08二叉树/05二叉树的直径.md.baiduyun.uploading.cfg",
    "剑指offer/02二叉树/06二叉树的镜像.md.baiduyun.uploading.cfg",
    "hot100/14贪心算法/assets/01买卖股票的最佳时机/file-20250522214932184.png",
    "hot100/08二叉树/assets/08验证二叉搜索搜索树/file-20250724002412032.png",
    "hot100/08二叉树/assets/08验证二叉搜索搜索树/file-20250724002426382.png",
    "hot100/08二叉树/assets/08验证二叉搜索搜索树/file-20250724000314823.png",
    "hot100/07链表/assets/11随机链表的复制（acm看一看）/file-20250724001130731.png",
    "hot100/07链表/assets/04环形链表（acm多做）/file-20250616232353136.png",
    "代码随想录/11图/assets/24A星算法/file-20250618175007997.png",
    "代码随想录/11图/assets/21bellman_ford算法之判断负权回路/file-20250617202357855.png",
    "代码随想录/11图/assets/20SPFA(bellman_ford队列优化版)/file-20250617174733945.png",
    "代码随想录/11图/assets/19bellman_ford算法/file-20250616201934571.png"
  ]
}